DynEnv/Ball.py
DynEnv/Car.py
DynEnv/DrivingEnvironment.py
DynEnv/Goalpost.py
DynEnv/Obstacle.py
DynEnv/Pedestrian.py
DynEnv/Road.py
DynEnv/RoboCupEnvironment.py
DynEnv/Robot.py
DynEnv/__init__.py
DynEnv/cutils.py
DynEnv/environment_base.py
DynEnv/examples/__init__.py
DynEnv/examples/analyse.py
DynEnv/examples/args.py
DynEnv/examples/generateReconExamples.py
DynEnv/examples/main.py
DynEnv/examples/play.py
DynEnv/examples/reconTrain.py
DynEnv/models/__init__.py
DynEnv/models/actor_critic.py
DynEnv/models/agent.py
DynEnv/models/icm.py
DynEnv/models/loss_descriptors.py
DynEnv/models/models.py
DynEnv/models/storage.py
DynEnv/models/train.py
DynEnv/utils/__init__.py
DynEnv/utils/base_vec_env.py
DynEnv/utils/logger.py
DynEnv/utils/renderer.py
DynEnv/utils/subproc_vec_env.py
DynEnv/utils/utils.py
DynEnv-2.0.dist-info/.gitignore
DynEnv-2.0.dist-info/METADATA
DynEnv-2.0.dist-info/WHEEL
DynEnv-2.0.dist-info/top_level.txt
DynEnv-2.0.dist-info/RECORD
