Metadata-Version: 2.1
Name: DynEnv
Version: 2.0
Summary: Dynamic RL Environments for Autonomous Driving and Robot Soccer
Home-page: https://github.com/szemenyeim/DynEnv
Author: Marton Szemenyei
Author-email: szemenyei@iit.bme.hu
License: UNKNOWN
Platform: UNKNOWN
Classifier: Programming Language :: Python :: 3
Classifier: License :: OSI Approved :: GNU General Public License v3 (GPLv3)
Classifier: Operating System :: OS Independent
Requires-Python: >=3.5
Requires-Dist: best
Requires-Dist: gym
Requires-Dist: h5py
Requires-Dist: imageio
Requires-Dist: matplotlib
Requires-Dist: numpy
Requires-Dist: opencv-python
Requires-Dist: pandas
Requires-Dist: pygame
Requires-Dist: pymc3
Requires-Dist: pymunk
Requires-Dist: scipy
Requires-Dist: torch
Requires-Dist: xlwt
